koalanlp/API.py
koalanlp/ExtUtil.py
koalanlp/Util.py
koalanlp/__init__.py
koalanlp/data.py
koalanlp/jvm.py
koalanlp/proc.py
koalanlp/types.py
koalanlp/jip/__init__.py
koalanlp/jip/cache.py
koalanlp/jip/index.py
koalanlp/jip/maven.py
koalanlp/jip/repository.py
koalanlp/jip/util.py
koalanlp/kiwi/__init__.py
koalanlp/kss/__init__.py
koalanlp-2.1.7.dist-info/LICENSE
koalanlp-2.1.7.dist-info/METADATA
koalanlp-2.1.7.dist-info/WHEEL
koalanlp-2.1.7.dist-info/top_level.txt
koalanlp-2.1.7.dist-info/RECORD
