Metadata-Version: 2.1
Name: koalanlp
Version: 2.1.7
Summary: Python wrapper for KoalaNLP
Home-page: https://koalanlp.github.io/python-support
Author: koalanlp
License: MIT
Project-URL: Issue Tracker, https://github.com/koalanlp/python-support/issues
Project-URL: Source Code, https://github.com/koalanlp/python-support
Keywords: korean,natural language processing,koalanlp,한국어 처리,한국어 분석,형태소,의존구문,구문구조,개체명,의미역
Platform: UNKNOWN
Classifier: Development Status :: 4 - Beta
Classifier: License :: OSI Approved :: MIT License
Classifier: Natural Language :: Korean
Classifier: Programming Language :: Python :: 3.5
Classifier: Programming Language :: Python :: 3.6
Classifier: Programming Language :: Python :: 3.7
Classifier: Topic :: Text Processing
Classifier: Topic :: Text Processing :: General
Classifier: Topic :: Text Processing :: Linguistic
Requires-Python: >=3.5
Requires-Dist: py4j (~=0.10)
Requires-Dist: requests (~=2.22)
Requires-Dist: kss (~=2.5.1)
